fivetran_connector_sdk/__init__.py
fivetran_connector_sdk/connector_helper.py
fivetran_connector_sdk/constants.py
fivetran_connector_sdk/helpers.py
fivetran_connector_sdk/initialisation_helper.py
fivetran_connector_sdk/logger.py
fivetran_connector_sdk/operation_stream.py
fivetran_connector_sdk/operations.py
fivetran_connector_sdk/protos/__init__.py
fivetran_connector_sdk/protos/common_pb2.py
fivetran_connector_sdk/protos/common_pb2.pyi
fivetran_connector_sdk/protos/common_pb2_grpc.py
fivetran_connector_sdk/protos/connector_sdk_pb2.py
fivetran_connector_sdk/protos/connector_sdk_pb2.pyi
fivetran_connector_sdk/protos/connector_sdk_pb2_grpc.py
fivetran_connector_sdk-2.5.1.dist-info/METADATA
fivetran_connector_sdk-2.5.1.dist-info/WHEEL
fivetran_connector_sdk-2.5.1.dist-info/entry_points.txt
fivetran_connector_sdk-2.5.1.dist-info/top_level.txt
fivetran_connector_sdk-2.5.1.dist-info/RECORD
