Metadata-Version: 2.4
Name: fivetran_connector_sdk
Version: 2.5.1
Summary: Build custom connectors on Fivetran platform
Author-email: Fivetran <developers@fivetran.com>
Project-URL: Homepage, https://fivetran.com/docs/connectors/connector-sdk
Project-URL: Github, https://github.com/fivetran/fivetran_connector_sdk
Project-URL: Changelog, https://fivetran.com/docs/connectors/connector-sdk/changelog
Classifier: Programming Language :: Python :: 3
Classifier: License :: OSI Approved :: MIT License
Classifier: Operating System :: OS Independent
Requires-Python: >=3.10
Requires-Dist: grpcio==1.76.0
Requires-Dist: grpcio-tools==1.76.0
Requires-Dist: requests==2.32.5
Requires-Dist: pipreqs-fivetran==1.1.0
Requires-Dist: prompt-toolkit==3.0.52
Requires-Dist: unidecode==1.4.0
Requires-Dist: pathspec==0.12.1
